{"wisdom_save":"7","reactions":[],"size":"huge","senses":"сліпий зір 60 ф, темний зір 120 ф, пасивна Увага 22","dexterity":"10","name":"Дорослий синій дракон","damage_immunities":"блискавка","intelligence_save":"","languages":"спільна, драконова","damage_resistances":"","intelligence":"16","speed":{"fly":"80 ф.","walk":"40 ф"},"charisma_save":"8","armor_class":"19","legendary_actions":[{"desc":"Дракон робить перевірку Мудрості (Увага).","name":"Пошук"},{"desc":"Дракон здійснює одну атаку хвостом.","name":"Атака хвостом"},{"desc":"Дракон б'є крилами. Кожна істота в межах 10 футів від дракона повинна зробити рятівний кидок Спритності з КС 20, або отримає 14 (2к6 + 7) дробильних ушкоджень і буде збита з ніг. Потім дракон може пролетіти до половини своєї швидкості польоту.","name":"Атака крилами (коштує 2 дії)"}],"special_abilities":[{"desc":"Якщо дракон провалює рятівний кидок, він може натомість обирати успіх.","name":"Легендарна стійкість (3\/день)"}],"armor_desc":"природна броня","constitution_save":"11","strength_save":"","strength":"25","dexterity_save":"5","legendary_desc":"Дракон може використати 3 легендарні дії, вибираючи з наведених далі можливостей. Тільки одну легендарну дію можна використати за раз, і тільки в кінці ходу іншої істоти. Дракон відновлює використані легендарні дії на початку свого ходу.","condition_immunities":"","slug":"adult_blue_dragon","hit_points":"225","challenge_rating":"16","constitution":"23","skills":{"сприйняття":"12","непомітність":"5"},"type":"Дракон","charisma":"25","wisdom":"15","alignment":" законний злий","actions":[],"damage_vulnerabilities":"","hit_dice":"18к12 + 108"}