{"dexterity":"12","name":"Сокиродзьоб","intelligence":"2","wisdom":"10","reactions":[],"hit_dice":"3к10 + 3","dexterity_save":"","charisma":"14","slug":"axe_beak","special_abilities":[],"challenge_rating":"1\/4","legendary_actions":"","damage_resistances":"","damage_immunities":"","senses":"пасивна Увага 10","charisma_save":"","wisdom_save":"","type":"Звір","legendary_desc":"","strength":"14","speed":{},"damage_vulnerabilities":"","strength_save":"","skills":{},"intelligence_save":"","armor_class":"","languages":"-","hit_points":"19","size":"large","armor_desc":"","alignment":" невизначений","constitution_save":"","actions":[{"desc":"_Атака зброєю ближнього бою:_ +4 до влучання, досяжність 5 ф, одна ціль. _Влучання:_ 6 (1к8 + 2) рубаних ушкоджень.","name":"Дзьоб"}],"condition_immunities":"","constitution":"12"}