{"intelligence":"10","legendary_actions":"","special_abilities":[{"desc":"Сектант має перевагу на рятівні кидки проти причарування та переляку.","name":"Темна відданість"}],"strength_save":"","damage_immunities":"","alignment":" будь-який не-добрий світогляд","wisdom_save":"","wisdom":"11","name":"Сектант","dexterity_save":"","challenge_rating":"1\/8","actions":[{"name":"Скимитар","desc":"_Атака зброєю ближнього бою:_ +3 до влучання, досяжність 5 ф, одна істота. _Влучання:_ 4 (1к6 + 1) рубаних ушкоджень."}],"constitution":"10","damage_vulnerabilities":"","size":"medium","senses":"пасивна Увага 10","speed":{},"languages":"будь-яка одна мова (зазвичай Спільна)","legendary_desc":"","dexterity":"12","reactions":[],"slug":"cultist","damage_resistances":"","strength":"11","armor_class":"12","skills":{"обман":"2","релігія":"2"},"armor_desc":"шкіряна броня","charisma_save":"","constitution_save":"","charisma":"11","hit_dice":"2к8","type":"Гуманоїд","intelligence_save":"","hit_points":"9","condition_immunities":""}