{"charisma":"18","dexterity_save":"","armor_class":"","legendary_actions":"","speed":{},"condition_immunities":"","wisdom_save":"","constitution_save":"","type":"Звір","constitution":"12","hit_dice":"3к10 + 3","senses":"пасивна Увага 10","slug":"draft_horse","name":"Кінь, тягловий [Draft horse]","dexterity":"10","wisdom":"11","intelligence":"2","size":"large","armor_desc":"","strength":"18","subtype":"","intelligence_save":"","charisma_save":"","damage_vulnerabilities":"","special_abilities":[{}],"legendary_desc":"","reactions":[],"damage_immunities":"","strength_save":"","alignment":" невизначений","damage_resistances":"","actions":[{"name":"Копита.","desc":"_Атака зброєю ближнього бою:_ +6 до влучання, досяжність 5 футів, одна ціль. _Влучання:_ 9 (2к4 + 4) дробильних ушкоджень."}],"languages":"-","skills":{},"hit_points":"19","challenge_rating":"1\/4"}