{"hit_points":"22","condition_immunities":"","intelligence":"14","armor_class":"11","size":"medium","armor_desc":"16 із дубовою шкірою","slug":"dryad","strength_save":"","speed":{},"type":"Фея","actions":[{"desc":"_Атака зброєю ближнього бою:_ +2 до влучання (+6 до влучання кийком), досяжність 5 ф, одна ціль. _Влучання:_ 2 (1к4) дробильних ушкоджень, або 8 (1к8 + 4) дробильних ушкоджень кийком.","name":"Фейські чари"}],"charisma":"10","constitution_save":"","damage_vulnerabilities":"","dexterity":"12","hit_dice":"5к8","challenge_rating":"1","charisma_save":"","intelligence_save":"","skills":{"сприйняття":"4","непомітність":"5"},"legendary_actions":"","damage_resistances":"","special_abilities":[{"desc":"Чаротворча здібність дріади - Харизма (КС чарів 14). Дріада може природно створювати наступні чари, не потребуючи матеріальних складових:","name":"Вроджене чарування"},{"name":"Магічна стійкість","desc":""},{"name":"Розмова зі звірами та рослинами","desc":""},{"desc":"","name":"Деревний шлях"}],"legendary_desc":"","reactions":[],"dexterity_save":"","alignment":"нейтральний","subtype":"","name":"Дріада","strength":"10","damage_immunities":"","senses":"темний зір 60 ф, пасивна Увага 14","languages":"ельфійська, сильван","wisdom":"15","constitution":"11","wisdom_save":""}