{"senses":"темний зір 120 ф, пасивна Увага 12","actions":[{"desc":"_Атака зброєю ближнього бою:_ +4 до влучання, досяжність 5 ф, одна ціль. _Влучання:_ 5 (1к6 + 2) колотих ушкоджень.","name":"Короткий меч"},{"desc":"_Далекобійна атака зброєю:_ +4 до влучання, відстань 30\/120 ф, одна ціль. _Влучання:_ 5 (1к6 + 2) колотих ушкоджень, і ціль повинна зробити рятівний кидок Статури з КС 13, або буде отруєна на 1 годину. Якщо рятівний кидок провалюється на 5 або більше, істота також непритомна, допоки отруєна таким чином. Істота прокидається, якщо зазнає пошкоджень, або якщо інша істота витрачає дію, щоб її розбудити.","name":"Ручний арбалет"}],"constitution_save":"","strength":"10","charisma_save":"","damage_resistances":"","legendary_actions":"","wisdom":"11","name":"Ельф, дроу","hit_dice":"3к8","speed":{},"reactions":[],"hit_points":"13","constitution":"10","armor_class":"15","armor_desc":"кольчужна сорочка","special_abilities":[{"desc":"Дроу мають перевагу на рятівні кидки проти причарування, і магія не може занурити дроу в сон.","name":"Спадщина фей"},{"desc":"Вродженою здібністю дроу до чарування є Харизма (КС 11). Він може природним чином створювати наступні чари, не потребуючи матеріальних складових:","name":"Вроджене чарування"},{"desc":"","name":"Чутливість до сонячного світла"}],"legendary_desc":"","damage_immunities":"","intelligence":"11","challenge_rating":"1\/4","dexterity":"14","dexterity_save":"","subtype":"ельф","languages":"ельфійська, підтемна","size":"medium","strength_save":"","intelligence_save":"","damage_vulnerabilities":"","wisdom_save":"","charisma":"10","type":"Гуманоїд","alignment":" нейтральний злий","condition_immunities":"","slug":"elf_drow","skills":{"сприйняття":"2","непомітність":"4"}}