{"dexterity":"9","hit_points":"138","type":"Велет","senses":"пасивна Увага 13","armor_class":"15","name":"Морозний велет","special_abilities":[],"constitution":"21","damage_vulnerabilities":"","languages":"велетова","strength":"23","legendary_desc":"","charisma_save":"4","hit_dice":"12к12 + 60","intelligence_save":"","slug":"frost_giant","actions":[{"desc":"Велет робить дві атаки дворучною сокирою.","name":"Дворучна сокира"},{"name":"Брила","desc":"_Атака зброєю ближнього бою:_ +9 до влучання, досяжність 10 ф, одна ціль. _Влучання:_ 25 (3к12 + 6) рубаних ушкоджень"}],"constitution_save":"8","wisdom":"10","strength_save":"","skills":{"атлетика":"9","сприйняття":"3"},"condition_immunities":"","alignment":"злий","wisdom_save":"3","size":"huge","dexterity_save":"","legendary_actions":"","speed":{},"challenge_rating":"8","reactions":[],"armor_desc":"клаптикова броня","intelligence":"9","charisma":"23","damage_resistances":"","subtype":"","damage_immunities":"холод"}