{"languages":"-","constitution":"13","charisma":"17","strength":"17","strength_save":"","damage_resistances":"","armor_class":"","skills":{"сприйняття":"4","непомітність":"5"},"armor_desc":"","hit_points":"52","charisma_save":"","special_abilities":[{"name":"Зупинка дихання","desc":"Перебуваючи не у воді, восьминіг може затримувати дихання на 1 годину."},{"desc":"Восьминіг має перевагу на перевірки Спритності (Непомітність), коли робить їх під водою. Дихання водою. Восьминіг може дихати тільки під водою.","name":"Підводне маскування"}],"intelligence_save":"","hit_dice":"8к10 + 8","alignment":"невизначений","damage_vulnerabilities":"","wisdom":"10","dexterity_save":"","legendary_actions":[],"intelligence":"4","condition_immunities":"","name":"Величезний восьминіг","size":"large","reactions":[],"senses":"темний зір 60 ф, пасивна Увага 14","speed":{"walk":"10 ф","swim":"60 ф."},"dexterity":"13","wisdom_save":"","type":"Звір","constitution_save":"","slug":"giant_octopus","subtype":"","damage_immunities":"","challenge_rating":"1","actions":[{"desc":"_Атака зброєю ближнього бою:_ +5 до влучання, досяжність 15 ф, одна ціль. _Влучання:_ 10 (2к6 + 3) дробильних ушкоджень. Якщо ціль є істотою, вона схоплена (КС втечі 16). Доки триває цей захват, ціль скута, а восьминіг не може використовувати свої щупальця проти іншої цілі.","name":"Чорнильна хмара (Відновлення після короткого або тривалого відпочинку)"}]}