{"damage_immunities":"","hit_points":"22","dexterity":"16","subtype":"","intelligence":"2","legendary_desc":"","type":"Звір","armor_class":"","special_abilities":[{},{"name":"Ехолокація.","desc":"Кажан не може користуватися сліпим зором, коли оглушений."},{"name":"Гострий слух.","desc":"Кажан має перевагу на перевірки Мудрості (Увага), що покладаються на слух."}],"skills":{},"speed":{"walk":"10 ф","fly":"60 ф."},"actions":[{"name":"Укус.","desc":"_Атака зброєю ближнього бою:_ +4 до влучання, досяжність 5 ф, одна істота. _Влучання:_ 5 (1к6 + 2) колотих ушкоджень."}],"charisma":"15","hit_dice":"4к10","dexterity_save":"","wisdom":"12","challenge_rating":"1\/4","legendary_actions":"","strength":"15","damage_vulnerabilities":"","size":"large","intelligence_save":"","name":"Величезний кажан [Giant bat]","slug":"giant_bat","charisma_save":"","condition_immunities":"","reactions":[],"strength_save":"","constitution_save":"","alignment":" невизначений","constitution":"11","languages":"-","senses":"сліпий зір 60 ф, пасивна Увага 11","damage_resistances":"","armor_desc":"","wisdom_save":""}