{"speed":{"fly":"50 ф.","walk":"10 ф"},"damage_vulnerabilities":"","name":"Величезна оса","legendary_desc":"","dexterity_save":"","armor_desc":"","intelligence_save":"","constitution_save":"","intelligence":"1","wisdom_save":"","size":"medium","hit_points":"13","actions":[{"desc":"_Атака зброєю ближнього бою:_ +4 до влучання, досяжність 5 ф, одна ціль. _Влучання:_ 5 (1к6 + 2) колотих ушкоджень, і ціль повинна зробити рятівний кидок Статури з КС 11, отримуючи 10 (3к6) ушкоджень отрутою в разі невдачі, або половину цих ушкоджень за умови успіху. Якщо ушкодження отрутою знижують пункти здоров'я цілі до 0, ціль стабільна, але отруєна на 1 годину, навіть після відновлення пунктів здоров'я, і поки триває це отруєння, ціль паралізована.","name":"Жало"}],"condition_immunities":"","subtype":"","wisdom":"10","charisma_save":"","armor_class":"","damage_resistances":"","constitution":"10","strength_save":"","damage_immunities":"","slug":"giant_wasp","legendary_actions":"","strength":"10","challenge_rating":"1\/2","special_abilities":[],"reactions":[],"dexterity":"14","type":"Звір","charisma":"10","senses":"пасивна Увага 10","skills":{},"alignment":" невизначений","hit_dice":"3к8","languages":"-"}