{"constitution":"10","legendary_actions":[],"damage_immunities":"","strength_save":"","damage_resistances":"","wisdom":"8","reactions":[],"damage_vulnerabilities":"","wisdom_save":"","speed":{},"armor_class":"15","armor_desc":"шкіряна броня, щит","charisma":"8","intelligence_save":"","hit_dice":"2к6","condition_immunities":"","charisma_save":"","challenge_rating":"1\/4","name":"Гоблін","dexterity_save":"","alignment":"злий","languages":"Спільна, ґоблінська","strength":"8","subtype":"","size":"medium","senses":"темний зір 60 ф., пасивна Увага 9","actions":[{"desc":"_Атака зброєю ближнього бою:_ +4 до влучання, досяжність 5 ф, одна дія. _Влучання:_ 5 (1к6 + 2) рубаних ушкоджень.","name":"Короткий лук"}],"dexterity":"14","type":"Малий","constitution_save":"","slug":"goblin","intelligence":"10","skills":{"непомітність":"6"},"hit_points":"7","special_abilities":[{"desc":"Гоблін може Відступити чи Затаїтися бонусною дією в кожний свій хід.","name":"Спритна втеча"}]}