{"legendary_desc":"","languages":"будь-яка одна мова (зазвичай спільна)","damage_vulnerabilities":"","hit_dice":"2к8 + 2","hit_points":"11","name":"Вартовий","damage_resistances":"","legendary_actions":"","challenge_rating":"1\/8","dexterity":"12","slug":"guard","alignment":" будь-який світогляд","charisma":"13","type":"Гуманоїд","skills":{"сприйняття":"2"},"size":"medium","speed":{},"reactions":[],"armor_desc":"кольчужна сорочка, щит","wisdom":"11","special_abilities":[],"strength":"13","strength_save":"","constitution_save":"","subtype":"","charisma_save":"","intelligence":"10","actions":[{"desc":"_Атака зброєю ближнього бою або далекобійна:_ +3 до влучання, досяжність 5 ф або відстань 20\/60 ф, одна ціль. _Влучання:_ 4 (1к6 + 1) колотих ушкоджень, або 5 (1к8 + 1) колотих ушкоджень, якщо використовує для атаки ближнього бою двома руками.","name":"Спис"}],"intelligence_save":"","condition_immunities":"","constitution":"12","damage_immunities":"","dexterity_save":"","armor_class":"16","wisdom_save":"","senses":"пасивна Увага 12"}