{"legendary_desc":"","alignment":" будь-який світогляд","strength":"16","slug":"half_red_dragon_veteran","dexterity":"13","intelligence":"10","charisma":"16","intelligence_save":"","skills":{"сприйняття":"2","атлетика":"5"},"charisma_save":"","wisdom":"11","size":"medium","speed":{},"damage_immunities":"","condition_immunities":"","wisdom_save":"","armor_desc":"лати","legendary_actions":"","senses":"сліпий зір 10 ф, темний зір 60 ф, пасивна Увага 12","languages":"спільна, драконова","strength_save":"","dexterity_save":"","reactions":[],"challenge_rating":"5","hit_points":"65","constitution":"14","hit_dice":"10к8 + 20","damage_resistances":"вогонь","damage_vulnerabilities":"","armor_class":"18","subtype":"","type":"Гуманоїд","name":"Напівчервоний дракон ветеран [Half-red dragon veteran]","constitution_save":"","special_abilities":[],"actions":[{"name":"Мультиатака","desc":"Ветеран здійснює дві атаки довгим мечем. Якщо він має напоготові короткий меч, то може також зробити атаку коротким мечем."},{"name":"Короткий меч","desc":"_Атака зброєю ближнього бою:_ +5 до влучання, досяжність 5 ф, одна ціль. _Влучання:_ 7 (1к8 + 3) рубаних ушкоджень або 8 (1к10 + 3) рубаних ушкоджень, якщо використовує обома руками."},{"name":"Важкий арбалет","desc":"_Атака зброєю ближнього бою:_ +5 до влучання, досяжність 5 ф, одна ціль. _Влучання:_ 6 (1к6 + 3) колотих ушкоджень."},{"name":"Вогняний подих. (Відновлення 5-6)","desc":"_Далекобійна атака зброєю:_ +3 до влучання, відстань 100\/400 ф, одна ціль. _Влучання:_ 6 (1к10 + 1) рубаних ушкоджень."}]}