{"wisdom_save":"","constitution":"14","special_abilities":[{},{"name":"Невидимість.","desc":"Переслідувач невидимий."},{"name":"Бездоганний мисливець.","desc":"Переслідувач отримує здобич від свого прикликача. Переслідувач знає напрямок до здобичі та відстань до неї, допоки вони перебувають на одному плані існування. Переслідувач також знає розташування прикликача."}],"size":"medium","charisma":"16","type":"Стихійник","subtype":"","strength_save":"","name":"Невидимий переслідувач [Invisible stalker]","damage_resistances":"дробильні, колоті та рубані від немагічних атак","armor_desc":"","intelligence_save":"","languages":"ауран, розуміє спільну, але не говорить нею","damage_immunities":"отрута","skills":{"непомітність":"10","сприйняття":"8"},"dexterity_save":"","legendary_actions":"","hit_dice":"16к8 + 32","slug":"invisible_stalker","damage_vulnerabilities":"","reactions":[],"challenge_rating":"6","constitution_save":"","intelligence":"10","dexterity":"19","actions":[{"name":"Мультиатака.","desc":"Переслідувач здійснює дві атаки стусанами."},{"name":"Стусан.","desc":"_Атака зброєю ближнього бою:_ +6 до влучання, досяжність 5 ф, одна ціль. _Влучання:_ 10 (2к6 + 3) дробильних ушкоджень."}],"strength":"16","wisdom":"15","alignment":" нейтральний","hit_points":"104","speed":{"fly":"50 ф (зависання)","walk":"50 ф"},"charisma_save":"","condition_immunities":"виснажений, схоплений, паралізований, скам'янілий, отруєний, збитий з ніг, скутий, непритомний","senses":"темний зір 60 ф, пасивна Увага 18","armor_class":"","legendary_desc":""}