{"name":"Ящеролюд","speed":{"swim":"30 ф.","walk":"30 ф"},"subtype":"ящеролюд","dexterity":"10","intelligence_save":"","strength_save":"","armor_desc":"природна броня, щит","challenge_rating":"1\/2","hit_dice":"4к8 + 4","armor_class":"15","constitution":"13","damage_resistances":"","reactions":[],"wisdom":"12","type":"Гуманоїд","condition_immunities":"","charisma":"15","charisma_save":"","wisdom_save":"","special_abilities":[{"desc":"Ящеролюд може затримувати дихання на 15 хвилин.","name":"Зупинка дихання"}],"slug":"lizardfolk","hit_points":"22","legendary_actions":"","strength":"15","damage_vulnerabilities":"","alignment":" нейтральний","size":"medium","senses":"пасивна Увага 13","constitution_save":"","languages":"драконова","legendary_desc":"","skills":{"непомітність":"4","виживання":"5","сприйняття":"3"},"actions":[{"name":"Мультиатака","desc":"Ящеролюд робить дві атаки ближнього бою, кожну іншою зброєю."},{"desc":"_Атака зброєю ближнього бою:_ +4 до влучання, досяжність 5 ф, одна ціль. _Влучання:_ 5 (1к6 + 2) колотих ушкоджень.","name":"Укус"},{"name":"Важка палиця","desc":"_Атака зброєю ближнього бою:_ +4 до влучання, досяжність 5 ф, одна ціль. _Влучання:_ 5 (1к6 + 2) дробильних ушкоджень."},{"desc":"_ _Атака зброєю ближнього бою або далекобійна:_ +4 до влучання, досяжність 5 ф або відстань 30\/120 ф, одна ціль. _Влучання:_ 5 (1к6 +2) колотих ушкоджень.","name":"Сулиця"},{"name":"Шипастий щит","desc":"_Атака зброєю ближнього бою:_ +4 до влучання, досяжність 5 ф, одна ціль. _Влучання:_ 5 (1к6 + 2) колотих ушкоджень."}],"intelligence":"7","dexterity_save":"","damage_immunities":""}