{"hit_points":"11","senses":"пасивна Увага 12","dexterity_save":"","armor_desc":"","damage_resistances":"","strength_save":"","constitution_save":"","name":"Мерфольк [Merfolk]","languages":"акван, спільна","special_abilities":[{},{"name":"Амфібія.","desc":"Мерфольк може дихати повітрям і водою."}],"armor_class":"","alignment":" нейтральний","intelligence":"11","charisma":"10","damage_vulnerabilities":"","constitution":"12","actions":[{"desc":"_Атака зброєю ближнього бою або далекобійна:_ +2 до влучання, досяжність 5 ф або відстань 20\/60 ф, одна ціль. _Влучання:_ 3 (1к6) колотих ушкоджень, або 4 (1к8) колотих ушкоджень, якщо використовує для атаки ближнього бою двома руками.","name":"Спис."}],"charisma_save":"","dexterity":"13","slug":"merfolk","intelligence_save":"","type":"Гуманоїд","skills":{"сприйняття":"2"},"legendary_desc":"","condition_immunities":"","wisdom_save":"","strength":"10","size":"medium","legendary_actions":"","wisdom":"11","speed":{"swim":"40 ф.","walk":"10 ф"},"reactions":[],"hit_dice":"2к8 + 2","damage_immunities":"","challenge_rating":"1\/8","subtype":"мерфольк"}