{"damage_vulnerabilities":"","senses":"пасивна Увага 12","subtype":"","constitution":"11","strength":"11","challenge_rating":"1\/8","damage_resistances":"","armor_desc":"шкіряна броня","slug":"noble","special_abilities":[],"alignment":"світогляд","dexterity":"12","wisdom_save":"","name":"Шляхтич","size":"medium","skills":{"обман":"5","переконливість":"5","здогадливість":"4"},"speed":{},"languages":"будь-які дві мови","charisma":"11","hit_points":"9","type":"Гуманоїд","condition_immunities":"","legendary_actions":[],"constitution_save":"","hit_dice":"2к8","damage_immunities":"","intelligence":"12","reactions":[{"name":"Парирування","desc":"Шляхтич додає 2 до свого КЗ проти однієї атаки ближнього бою, яка мала б по ньому влучити. Щоб зробити це, шляхтич повинен бачити нападника й повинен тримати зброю ближнього бою."}],"armor_class":"15","strength_save":"","wisdom":"14","charisma_save":"","actions":[],"intelligence_save":"","dexterity_save":""}