{"strength_save":"","reactions":[],"subtype":"","wisdom":"11","dexterity":"10","skills":{},"damage_vulnerabilities":"","senses":"пасивна Увага 10","constitution_save":"","constitution":"13","hit_dice":"2к8 + 2","armor_class":"","damage_immunities":"","charisma":"15","intelligence_save":"","name":"Поні","intelligence":"2","actions":[{"desc":"_Атака зброєю ближнього бою:_ +4 до влучання, досяжність 5 ф, одна ціль. _Влучання:_ 7 (2к4 + 2) дробильних ушкоджень.","name":"Копита"}],"type":"Звір","wisdom_save":"","hit_points":"11","charisma_save":"","alignment":" невизначений","size":"medium","dexterity_save":"","legendary_actions":"","slug":"pony","challenge_rating":"","special_abilities":[],"speed":{},"legendary_desc":"","strength":"15","damage_resistances":"","condition_immunities":"","languages":"-","armor_desc":""}