{"damage_immunities":"","speed":{},"armor_desc":"природна броня","dexterity_save":"","intelligence_save":"","alignment":" невизначений","damage_resistances":"","condition_immunities":"","damage_vulnerabilities":"","legendary_actions":"","armor_class":"14","intelligence":"2","challenge_rating":"1\/2","legendary_desc":"","strength":"13","hit_points":"27","wisdom":"13","special_abilities":[{"name":"Чуття заліза","desc":"Іржавник може визначити за запахом розташування залізовмісних металів у межах 30 футів від себе."},{"desc":"Будь-яка немагічна зброя, виготовлена з металу, іржавіє при влучанні по іржавнику. Після завдання ушкоджень зброя отримує постійний та накопичувальний штраф -1 до кидків ушкоджень. Якщо цей штраф досягає -5, зброя руйнується. Немагічні боєприпаси з металу, що влучають по іржавнику, руйнуються після завдання ушкоджень.","name":"Корозія металу"}],"slug":"rust_monster","senses":"темний зір 60 ф., пасивна Увага 11","wisdom_save":"","hit_dice":"5к8 + 5","languages":"-","skills":{},"strength_save":"","dexterity":"12","reactions":[],"subtype":"","constitution":"13","actions":[{"desc":"_Атака зброєю ближнього бою:_ +3 до влучання, досяжність 5 ф, одна ціль. _Влучання:_ 5 (1к8 + 1) колотих ушкоджень.","name":"Укус"},{"name":"Антена","desc":"Іржавник спричиняє корозію немагічного залізовмісного металевого предмета, який може бачити в межах 5 футів від себе. Якщо предмет ніхто не тримає при собі, дотик знищує 1-футовий куб цього предмета. Якщо предмет тримає при собі істота, ця істота може зробити рятівний кидок Спритності з КС 11, аби уникнути дотику монстра."}],"charisma":"13","charisma_save":"","name":"Іржавник","constitution_save":"","size":"medium","type":"Чудовисько"}