{"damage_resistances":"","charisma":"13","special_abilities":[{"name":"Чуття заліза.","desc":"Іржавник може визначити за запахом розташування залізовмісних металів у межах 30 футів від себе."},{"desc":"Будь-яка немагічна зброя, виготовлена з металу, іржавіє при влучанні по іржавнику. Після завдання ушкоджень зброя отримує постійний та накопичувальний штраф -1 до кидків ушкоджень. Якщо цей штраф досягає -5, зброя руйнується. Немагічні боєприпаси з металу, що влучають по іржавнику, руйнуються після завдання ушкоджень.","name":"Корозія металу."}],"speed":{},"senses":"темний зір 60 ф., пасивна Увага 11","hit_points":"27","size":"medium","hit_dice":"5к8 + 5","wisdom":"13","name":"Іржавник [Rust monster]","dexterity":"12","strength_save":"","armor_class":"14","intelligence_save":"","intelligence":"2","skills":{},"condition_immunities":"","languages":"-","subtype":"","armor_desc":"природна броня","damage_vulnerabilities":"","slug":"rust_monster","constitution":"13","damage_immunities":"","challenge_rating":"1\/2","constitution_save":"","alignment":" невизначений","reactions":[],"type":"Чудовисько","wisdom_save":"","dexterity_save":"","actions":[{"desc":"_Атака зброєю ближнього бою:_ +3 до влучання, досяжність 5 ф, одна ціль. _Влучання:_ 5 (1к8 + 1) колотих ушкоджень.","name":"Укус."},{"name":"Антена.","desc":"Іржавник спричиняє корозію немагічного залізовмісного металевого предмета, який може бачити в межах 5 футів від себе. Якщо предмет ніхто не тримає при собі, дотик знищує 1-футовий куб цього предмета. Якщо предмет тримає при собі істота, ця істота може зробити рятівний кидок Спритності з КС 11, аби уникнути дотику монстра.    \n\nЯкщо предмет, котрого торкнувся іржавник, є металевим обладунком або металевим щитом, який хтось тримає при собі, такий предмет отримує постійний та накопичувальний штраф -1 до КЗ, наданого цим предметом. Обладунок, чий КЗ знижується до 10, або щит, чий захист знижується до бонусу 0, ламаються. Якщо цей предмет є металевою зброєю, яку хтось тримає, вона іржавіє, як описано в рисі Корозія металу."}],"strength":"13","legendary_desc":"","legendary_actions":"","charisma_save":""}