{"senses":"пасивна Увага 12","condition_immunities":"","wisdom_save":"","armor_desc":"шкіряна броня","type":"Фея","hit_points":"31","dexterity_save":"","intelligence_save":"","actions":[{"name":"Таран","desc":"* 6 (2к4 + 1) дробильних ушкоджень."},{"name":"Короткий меч","desc":"_Атака зброєю ближнього бою:_ +5 до влучання, досяжність 5 ф, одна ціль. _Влучання:_ 6 (1к6 + 3) колотих ушкоджень."},{"desc":"_Далекобійна атака зброєю:_ +5 до влучання, відстань 80\/320 ф, одна ціль. _Влучання:_ 6 (1к6 + 3) колотих ушкоджень.","name":"Короткий лук"}],"name":"Сатир","skills":{"непомітність":"5","артистичність":"6","сприйняття":"2"},"size":"medium","constitution_save":"","hit_dice":"7к8","special_abilities":[{"name":"Магічна стійкість","desc":"Сатир має перевагу на рятівні кидки проти чарів та інших магічних ефектів."}],"legendary_actions":"","constitution":"11","damage_immunities":"","strength_save":"","armor_class":"14","slug":"satyr","intelligence":"12","damage_resistances":"","dexterity":"16","strength":"12","alignment":" хаотичний нейтральний","subtype":"","wisdom":"10","charisma":"12","challenge_rating":"1\/2","damage_vulnerabilities":"","legendary_desc":"","charisma_save":"","languages":"спільна, ельфійська, сильван","reactions":[],"speed":{}}