{"languages":"спільна, драконова","charisma_save":"5","dexterity":"12","type":"Дракон","skills":{"сприйняття":"7","непомітність":"4","обман":"5"},"strength_save":"","armor_class":"17","condition_immunities":"","intelligence_save":"","subtype":"","alignment":" хаотичний добрий","dexterity_save":"4","wisdom":"13","senses":"сліпий зір 30 ф, темний зір 120 ф, пасивна Увага 17","hit_points":"119","constitution":"17","name":"Молодий мідний дракон [Young copper dragon]","strength":"19","charisma":"19","legendary_desc":"","size":"large","intelligence":"16","damage_resistances":"","slug":"young_copper_dragon","legendary_actions":"","reactions":[],"wisdom_save":"4","damage_immunities":"кислота","hit_dice":"14к10 + 42","armor_desc":"природна броня","challenge_rating":"7","special_abilities":[{}],"damage_vulnerabilities":"","speed":{"walk":"40 ф","fly":"80 ф."},"actions":[{"desc":"Дракон здійснює три атаки: одну укусом та дві - пазурами.","name":"Мультиатака."},{"name":"Укус.","desc":"_Атака зброєю ближнього бою:_ +7 до влучання, досяжність 10 ф, одна ціль. _Влучання:_ 14 (2к10 + 4) колотих ушкоджень."},{"desc":"_Атака зброєю ближнього бою:_ +7 до влучання, досяжність 5 ф, одна ціль. _Влучання:_ 11 (2к6 + 4) рубаних ушкоджень.","name":"Пазурі."},{"name":"Зброя подиху (Відновлення 5-6).","desc":"Дракон використовує один із наступних видів зброї подиху."},{"desc":"Дракон видихає кислоту лінією завдовжки 40 ф та завширшки 5 ф. Кожна істота в лінії повинна здійснити рятівний кидок Спритності з КС 14, отримуючи 40 (9к8) ушкоджень кислотою у разі невдачі або половину цих ушкоджень за умови успіху.","name":"Кислотне дихання."},{"desc":"Дракон видихає газ 30-футовим конусом. Кожна істота в цій області повинна зробити рятівний кидок Статури з КС 14. У разі невдачі істота не може використовувати реакції, її швидкість зменшена вдвічі, і вона не може здійснювати більше однієї атаки в свій хід. На додачу істота може використовувати в свій хід або дію, або бонусну дію, але не обидві. Ці ефекти тривають 1 хвилину. Істота може повторювати рятівний кидок в кінці кожного свого ходу, припиняючи ефект у разі успіху.","name":"Повільне дихання."}],"constitution_save":"6"}